README.md
setup.cfg
setup.py
halohalo/__init__.py
halohalo/main.py
halohalo.egg-info/PKG-INFO
halohalo.egg-info/SOURCES.txt
halohalo.egg-info/dependency_links.txt
halohalo.egg-info/top_level.txt
halohalo/experimentation/__init__.py
halohalo/experimentation/experimentation.py
halohalo/service/__init__.py
halohalo/service/service.py