Metadata-Version: 1.0
Name: halohalo
Version: 0.0.13
Summary: Randomized AB Testing Library used for integrating with ML Deployments
Home-page: UNKNOWN
Author: Miles Ong
Author-email: UNKNOWN
License: MIT
Platform: UNKNOWN
